[
  {
    "name": "Riverfront Development Project",
    "category": "metro",
    "department": "Urban Development Authority",
    "contractor": "NBCC India Ltd",
    "budget": "\u20b9542 Cr",
    "start_date": "2023-12-17",
    "completion_date": "2025-04-05",
    "status": "completed",
    "progress": "93",
    "area": "Hyderabad",
    "district": "Hyderabad",
    "lat": "17.39827",
    "lng": "78.473588",
    "description": "Ongoing public infrastructure development initiative under government planning.",
    "impact": "Expected 15% improvement in public services"
  },
  {
    "name": "National Highway Capacity Expansion",
    "category": "road",
    "department": "Ministry of Road Transport and Highways",
    "contractor": "GMR Infrastructure",
    "budget": "\u20b9578 Cr",
    "start_date": "2023-08-26",
    "completion_date": "2025-06-18",
    "status": "in progress",
    "progress": "65",
    "area": "Mumbai",
    "district": "Mumbai Suburban",
    "lat": "19.088063",
    "lng": "72.864254",
    "description": "Ongoing public infrastructure development initiative under government planning.",
    "impact": "Expected 31% improvement in public services"
  },
  {
    "name": "Multi-Speciality Government Hospital Expansion",
    "category": "sewage",
    "department": "Ministry of Road Transport and Highways",
    "contractor": "NBCC India Ltd",
    "budget": "\u20b9646 Cr",
    "start_date": "2024-06-15",
    "completion_date": "2026-08-20",
    "status": "planned",
    "progress": "7",
    "area": "Mumbai",
    "district": "Mumbai Suburban",
    "lat": "19.029851",
    "lng": "72.875662",
    "description": "Ongoing public infrastructure development initiative under government planning.",
    "impact": "Expected 28% improvement in public services"
  },
  {
    "name": "Metro Corridor Phase II Extension",
    "category": "building",
    "department": "Ministry of Road Transport and Highways",
    "contractor": "GMR Infrastructure",
    "budget": "\u20b9396 Cr",
    "start_date": "2023-11-11",
    "completion_date": "2025-10-12",
    "status": "planned",
    "progress": "7",
    "area": "Mumbai",
    "district": "Mumbai Suburban",
    "lat": "19.038031",
    "lng": "72.841717",
    "description": "Ongoing public infrastructure development initiative under government planning.",
    "impact": "Expected 29% improvement in public services"
  },
  {
    "name": "Urban Flood Mitigation Drainage System",
    "category": "metro",
    "department": "Smart Cities Mission",
    "contractor": "Tata Projects Ltd",
    "budget": "\u20b9154 Cr",
    "start_date": "2023-06-27",
    "completion_date": "2025-09-26",
    "status": "in progress",
    "progress": "75",
    "area": "Mumbai",
    "district": "Mumbai Suburban",
    "lat": "19.124725",
    "lng": "72.911163",
    "description": "Ongoing public infrastructure development initiative under government planning.",
    "impact": "Expected 41% improvement in public services"
  },
  {
    "name": "National Highway Capacity Expansion",
    "category": "metro",
    "department": "Ministry of Health",
    "contractor": "NBCC India Ltd",
    "budget": "\u20b9768 Cr",
    "start_date": "2023-07-09",
    "completion_date": "2025-05-03",
    "status": "in progress",
    "progress": "48",
    "area": "Delhi",
    "district": "New Delhi",
    "lat": "28.656773",
    "lng": "77.232645",
    "description": "Ongoing public infrastructure development initiative under government planning.",
    "impact": "Expected 30% improvement in public services"
  },
  {
    "name": "Riverfront Development Project",
    "category": "hospital",
    "department": "Ministry of Health",
    "contractor": "Larsen & Toubro Ltd",
    "budget": "\u20b9579 Cr",
    "start_date": "2023-11-26",
    "completion_date": "2025-06-08",
    "status": "planned",
    "progress": "15",
    "area": "Delhi",
    "district": "New Delhi",
    "lat": "28.626873",
    "lng": "77.237545",
    "description": "Ongoing public infrastructure development initiative under government planning.",
    "impact": "Expected 27% improvement in public services"
  },
  {
    "name": "Riverfront Development Project",
    "category": "building",
    "department": "Ministry of Health",
    "contractor": "Larsen & Toubro Ltd",
    "budget": "\u20b9785 Cr",
    "start_date": "2023-08-15",
    "completion_date": "2025-09-08",
    "status": "planned",
    "progress": "9",
    "area": "Kolkata",
    "district": "Kolkata",
    "lat": "22.596419",
    "lng": "88.329493",
    "description": "Ongoing public infrastructure development initiative under government planning.",
    "impact": "Expected 39% improvement in public services"
  },
  {
    "name": "City Bus Rapid Transit Corridor",
    "category": "road",
    "department": "Ministry of Road Transport and Highways",
    "contractor": "NBCC India Ltd",
    "budget": "\u20b9647 Cr",
    "start_date": "2024-02-06",
    "completion_date": "2026-02-24",
    "status": "planned",
    "progress": "13",
    "area": "Kolkata",
    "district": "Kolkata",
    "lat": "22.575116",
    "lng": "88.395087",
    "description": "Ongoing public infrastructure development initiative under government planning.",
    "impact": "Expected 41% improvement in public services"
  },
  {
    "name": "Metro Corridor Phase II Extension",
    "category": "road",
    "department": "Municipal Corporation",
    "contractor": "Shapoorji Pallonji Group",
    "budget": "\u20b9135 Cr",
    "start_date": "2024-05-03",
    "completion_date": "2025-10-27",
    "status": "in progress",
    "progress": "34",
    "area": "Pune",
    "district": "Pune",
    "lat": "18.504832",
    "lng": "73.900389",
    "description": "Ongoing public infrastructure development initiative under government planning.",
    "impact": "Expected 20% improvement in public services"
  },
  {
    "name": "Smart City Integrated Command Center",
    "category": "water",
    "department": "Municipal Corporation",
    "contractor": "Larsen & Toubro Ltd",
    "budget": "\u20b9746 Cr",
    "start_date": "2024-02-01",
    "completion_date": "2025-04-28",
    "status": "in progress",
    "progress": "52",
    "area": "Mumbai",
    "district": "Mumbai Suburban",
    "lat": "19.116895",
    "lng": "72.887695",
    "description": "Ongoing public infrastructure development initiative under government planning.",
    "impact": "Expected 22% improvement in public services"
  },
  {
    "name": "City Bus Rapid Transit Corridor",
    "category": "sewage",
    "department": "Municipal Corporation",
    "contractor": "Shapoorji Pallonji Group",
    "budget": "\u20b9268 Cr",
    "start_date": "2024-03-19",
    "completion_date": "2026-08-17",
    "status": "in progress",
    "progress": "39",
    "area": "Mumbai",
    "district": "Mumbai Suburban",
    "lat": "19.040101",
    "lng": "72.877945",
    "description": "Ongoing public infrastructure development initiative under government planning.",
    "impact": "Expected 41% improvement in public services"
  },
  {
    "name": "Eastern Peripheral Expressway Upgrade",
    "category": "hospital",
    "department": "Smart Cities Mission",
    "contractor": "NBCC India Ltd",
    "budget": "\u20b9359 Cr",
    "start_date": "2023-04-11",
    "completion_date": "2024-04-02",
    "status": "in progress",
    "progress": "36",
    "area": "Kolkata",
    "district": "Kolkata",
    "lat": "22.576268",
    "lng": "88.340027",
    "description": "Ongoing public infrastructure development initiative under government planning.",
    "impact": "Expected 21% improvement in public services"
  },
  {
    "name": "Multi-Speciality Government Hospital Expansion",
    "category": "building",
    "department": "Urban Development Authority",
    "contractor": "NBCC India Ltd",
    "budget": "\u20b9370 Cr",
    "start_date": "2024-06-27",
    "completion_date": "2026-09-27",
    "status": "in progress",
    "progress": "22",
    "area": "Bangalore",
    "district": "Bangalore Urban",
    "lat": "13.010966",
    "lng": "77.577041",
    "description": "Ongoing public infrastructure development initiative under government planning.",
    "impact": "Expected 38% improvement in public services"
  },
  {
    "name": "Urban Flood Mitigation Drainage System",
    "category": "building",
    "department": "Urban Development Authority",
    "contractor": "Larsen & Toubro Ltd",
    "budget": "\u20b9297 Cr",
    "start_date": "2023-04-25",
    "completion_date": "2024-07-22",
    "status": "in progress",
    "progress": "58",
    "area": "Hyderabad",
    "district": "Hyderabad",
    "lat": "17.354719",
    "lng": "78.489209",
    "description": "Ongoing public infrastructure development initiative under government planning.",
    "impact": "Expected 40% improvement in public services"
  },
  {
    "name": "City Bus Rapid Transit Corridor",
    "category": "sewage",
    "department": "Ministry of Health",
    "contractor": "Larsen & Toubro Ltd",
    "budget": "\u20b9141 Cr",
    "start_date": "2024-01-28",
    "completion_date": "2026-02-12",
    "status": "planned",
    "progress": "10",
    "area": "Delhi",
    "district": "New Delhi",
    "lat": "28.595534",
    "lng": "77.194239",
    "description": "Ongoing public infrastructure development initiative under government planning.",
    "impact": "Expected 33% improvement in public services"
  },
  {
    "name": "Water Supply Pipeline Modernization",
    "category": "hospital",
    "department": "Smart Cities Mission",
    "contractor": "GMR Infrastructure",
    "budget": "\u20b9188 Cr",
    "start_date": "2024-08-19",
    "completion_date": "2026-11-16",
    "status": "in progress",
    "progress": "82",
    "area": "Pune",
    "district": "Pune",
    "lat": "18.547622",
    "lng": "73.878402",
    "description": "Ongoing public infrastructure development initiative under government planning.",
    "impact": "Expected 43% improvement in public services"
  },
  {
    "name": "Water Supply Pipeline Modernization",
    "category": "sewage",
    "department": "Ministry of Health",
    "contractor": "Larsen & Toubro Ltd",
    "budget": "\u20b9497 Cr",
    "start_date": "2023-06-23",
    "completion_date": "2025-02-02",
    "status": "in progress",
    "progress": "32",
    "area": "Pune",
    "district": "Pune",
    "lat": "18.483201",
    "lng": "73.887772",
    "description": "Ongoing public infrastructure development initiative under government planning.",
    "impact": "Expected 38% improvement in public services"
  },
  {
    "name": "Water Supply Pipeline Modernization",
    "category": "water",
    "department": "Ministry of Health",
    "contractor": "Larsen & Toubro Ltd",
    "budget": "\u20b9108 Cr",
    "start_date": "2024-05-09",
    "completion_date": "2025-06-16",
    "status": "in progress",
    "progress": "25",
    "area": "Mumbai",
    "district": "Mumbai Suburban",
    "lat": "19.098271",
    "lng": "72.833984",
    "description": "Ongoing public infrastructure development initiative under government planning.",
    "impact": "Expected 24% improvement in public services"
  },
  {
    "name": "Metro Corridor Phase II Extension",
    "category": "building",
    "department": "Ministry of Health",
    "contractor": "Shapoorji Pallonji Group",
    "budget": "\u20b9129 Cr",
    "start_date": "2024-01-31",
    "completion_date": "2025-07-28",
    "status": "in progress",
    "progress": "46",
    "area": "Delhi",
    "district": "New Delhi",
    "lat": "28.574456",
    "lng": "77.238619",
    "description": "Ongoing public infrastructure development initiative under government planning.",
    "impact": "Expected 42% improvement in public services"
  },
  {
    "name": "Urban Flood Mitigation Drainage System",
    "category": "hospital",
    "department": "Urban Development Authority",
    "contractor": "Larsen & Toubro Ltd",
    "budget": "\u20b9563 Cr",
    "start_date": "2023-09-05",
    "completion_date": "2025-11-25",
    "status": "planned",
    "progress": "8",
    "area": "Pune",
    "district": "Pune",
    "lat": "18.497966",
    "lng": "73.847712",
    "description": "Ongoing public infrastructure development initiative under government planning.",
    "impact": "Expected 20% improvement in public services"
  },
  {
    "name": "Smart City Integrated Command Center",
    "category": "sewage",
    "department": "Municipal Corporation",
    "contractor": "NBCC India Ltd",
    "budget": "\u20b9183 Cr",
    "start_date": "2024-01-04",
    "completion_date": "2025-08-21",
    "status": "in progress",
    "progress": "44",
    "area": "Kolkata",
    "district": "Kolkata",
    "lat": "22.527746",
    "lng": "88.36595",
    "description": "Ongoing public infrastructure development initiative under government planning.",
    "impact": "Expected 35% improvement in public services"
  },
  {
    "name": "Eastern Peripheral Expressway Upgrade",
    "category": "building",
    "department": "Smart Cities Mission",
    "contractor": "Larsen & Toubro Ltd",
    "budget": "\u20b9315 Cr",
    "start_date": "2023-05-20",
    "completion_date": "2025-04-19",
    "status": "planned",
    "progress": "9",
    "area": "Chennai",
    "district": "Chennai",
    "lat": "13.058894",
    "lng": "80.287169",
    "description": "Ongoing public infrastructure development initiative under government planning.",
    "impact": "Expected 38% improvement in public services"
  },
  {
    "name": "Smart City Integrated Command Center",
    "category": "road",
    "department": "Smart Cities Mission",
    "contractor": "NBCC India Ltd",
    "budget": "\u20b9379 Cr",
    "start_date": "2023-01-15",
    "completion_date": "2024-04-02",
    "status": "in progress",
    "progress": "41",
    "area": "Mumbai",
    "district": "Mumbai Suburban",
    "lat": "19.051513",
    "lng": "72.832892",
    "description": "Ongoing public infrastructure development initiative under government planning.",
    "impact": "Expected 29% improvement in public services"
  },
  {
    "name": "Affordable Housing Redevelopment Scheme",
    "category": "road",
    "department": "Ministry of Road Transport and Highways",
    "contractor": "Shapoorji Pallonji Group",
    "budget": "\u20b9331 Cr",
    "start_date": "2023-02-13",
    "completion_date": "2024-09-04",
    "status": "completed",
    "progress": "95",
    "area": "Hyderabad",
    "district": "Hyderabad",
    "lat": "17.377696",
    "lng": "78.512665",
    "description": "Ongoing public infrastructure development initiative under government planning.",
    "impact": "Expected 19% improvement in public services"
  },
  {
    "name": "Eastern Peripheral Expressway Upgrade",
    "category": "sewage",
    "department": "Ministry of Road Transport and Highways",
    "contractor": "Shapoorji Pallonji Group",
    "budget": "\u20b955 Cr",
    "start_date": "2023-12-11",
    "completion_date": "2025-03-15",
    "status": "in progress",
    "progress": "28",
    "area": "Kolkata",
    "district": "Kolkata",
    "lat": "22.533045",
    "lng": "88.380722",
    "description": "Ongoing public infrastructure development initiative under government planning.",
    "impact": "Expected 45% improvement in public services"
  },
  {
    "name": "Affordable Housing Redevelopment Scheme",
    "category": "hospital",
    "department": "Urban Development Authority",
    "contractor": "Tata Projects Ltd",
    "budget": "\u20b9586 Cr",
    "start_date": "2024-08-11",
    "completion_date": "2026-05-01",
    "status": "in progress",
    "progress": "22",
    "area": "Mumbai",
    "district": "Mumbai Suburban",
    "lat": "19.047558",
    "lng": "72.909043",
    "description": "Ongoing public infrastructure development initiative under government planning.",
    "impact": "Expected 19% improvement in public services"
  },
  {
    "name": "Urban Flood Mitigation Drainage System",
    "category": "sewage",
    "department": "Smart Cities Mission",
    "contractor": "NBCC India Ltd",
    "budget": "\u20b9648 Cr",
    "start_date": "2023-12-28",
    "completion_date": "2025-07-02",
    "status": "completed",
    "progress": "93",
    "area": "Delhi",
    "district": "New Delhi",
    "lat": "28.577743",
    "lng": "77.201448",
    "description": "Ongoing public infrastructure development initiative under government planning.",
    "impact": "Expected 43% improvement in public services"
  },
  {
    "name": "Urban Flood Mitigation Drainage System",
    "category": "metro",
    "department": "Urban Development Authority",
    "contractor": "Larsen & Toubro Ltd",
    "budget": "\u20b9218 Cr",
    "start_date": "2024-07-12",
    "completion_date": "2026-08-29",
    "status": "in progress",
    "progress": "28",
    "area": "Bangalore",
    "district": "Bangalore Urban",
    "lat": "12.971243",
    "lng": "77.608636",
    "description": "Ongoing public infrastructure development initiative under government planning.",
    "impact": "Expected 44% improvement in public services"
  },
  {
    "name": "Affordable Housing Redevelopment Scheme",
    "category": "water",
    "department": "Ministry of Road Transport and Highways",
    "contractor": "NBCC India Ltd",
    "budget": "\u20b9530 Cr",
    "start_date": "2024-08-04",
    "completion_date": "2026-09-03",
    "status": "in progress",
    "progress": "50",
    "area": "Kolkata",
    "district": "Kolkata",
    "lat": "22.553909",
    "lng": "88.374839",
    "description": "Ongoing public infrastructure development initiative under government planning.",
    "impact": "Expected 44% improvement in public services"
  },
  {
    "name": "Metro Corridor Phase II Extension",
    "category": "sewage",
    "department": "Smart Cities Mission",
    "contractor": "GMR Infrastructure",
    "budget": "\u20b9699 Cr",
    "start_date": "2023-11-14",
    "completion_date": "2025-03-24",
    "status": "in progress",
    "progress": "44",
    "area": "Mumbai",
    "district": "Mumbai Suburban",
    "lat": "19.039574",
    "lng": "72.845262",
    "description": "Ongoing public infrastructure development initiative under government planning.",
    "impact": "Expected 33% improvement in public services"
  },
  {
    "name": "Affordable Housing Redevelopment Scheme",
    "category": "sewage",
    "department": "Ministry of Health",
    "contractor": "GMR Infrastructure",
    "budget": "\u20b9766 Cr",
    "start_date": "2023-12-22",
    "completion_date": "2026-05-10",
    "status": "in progress",
    "progress": "22",
    "area": "Chennai",
    "district": "Chennai",
    "lat": "13.070658",
    "lng": "80.304671",
    "description": "Ongoing public infrastructure development initiative under government planning.",
    "impact": "Expected 24% improvement in public services"
  },
  {
    "name": "Urban Flood Mitigation Drainage System",
    "category": "road",
    "department": "Urban Development Authority",
    "contractor": "NBCC India Ltd",
    "budget": "\u20b966 Cr",
    "start_date": "2023-05-11",
    "completion_date": "2025-05-12",
    "status": "in progress",
    "progress": "84",
    "area": "Bangalore",
    "district": "Bangalore Urban",
    "lat": "13.01642",
    "lng": "77.622024",
    "description": "Ongoing public infrastructure development initiative under government planning.",
    "impact": "Expected 41% improvement in public services"
  },
  {
    "name": "Riverfront Development Project",
    "category": "building",
    "department": "Ministry of Road Transport and Highways",
    "contractor": "Tata Projects Ltd",
    "budget": "\u20b9388 Cr",
    "start_date": "2024-03-26",
    "completion_date": "2025-04-30",
    "status": "in progress",
    "progress": "31",
    "area": "Kolkata",
    "district": "Kolkata",
    "lat": "22.597241",
    "lng": "88.358056",
    "description": "Ongoing public infrastructure development initiative under government planning.",
    "impact": "Expected 25% improvement in public services"
  },
  {
    "name": "Eastern Peripheral Expressway Upgrade",
    "category": "building",
    "department": "Urban Development Authority",
    "contractor": "GMR Infrastructure",
    "budget": "\u20b9110 Cr",
    "start_date": "2024-01-23",
    "completion_date": "2025-06-19",
    "status": "planned",
    "progress": "11",
    "area": "Hyderabad",
    "district": "Hyderabad",
    "lat": "17.417349",
    "lng": "78.47901",
    "description": "Ongoing public infrastructure development initiative under government planning.",
    "impact": "Expected 31% improvement in public services"
  },
  {
    "name": "Urban Flood Mitigation Drainage System",
    "category": "hospital",
    "department": "Municipal Corporation",
    "contractor": "NBCC India Ltd",
    "budget": "\u20b9540 Cr",
    "start_date": "2023-09-22",
    "completion_date": "2024-09-06",
    "status": "in progress",
    "progress": "58",
    "area": "Hyderabad",
    "district": "Hyderabad",
    "lat": "17.38027",
    "lng": "78.480402",
    "description": "Ongoing public infrastructure development initiative under government planning.",
    "impact": "Expected 22% improvement in public services"
  },
  {
    "name": "Water Supply Pipeline Modernization",
    "category": "road",
    "department": "Municipal Corporation",
    "contractor": "Shapoorji Pallonji Group",
    "budget": "\u20b9445 Cr",
    "start_date": "2023-03-15",
    "completion_date": "2025-04-15",
    "status": "in progress",
    "progress": "50",
    "area": "Mumbai",
    "district": "Mumbai Suburban",
    "lat": "19.036366",
    "lng": "72.916423",
    "description": "Ongoing public infrastructure development initiative under government planning.",
    "impact": "Expected 26% improvement in public services"
  },
  {
    "name": "Smart City Integrated Command Center",
    "category": "road",
    "department": "Urban Development Authority",
    "contractor": "NBCC India Ltd",
    "budget": "\u20b9767 Cr",
    "start_date": "2024-01-16",
    "completion_date": "2026-02-08",
    "status": "in progress",
    "progress": "66",
    "area": "Mumbai",
    "district": "Mumbai Suburban",
    "lat": "19.079464",
    "lng": "72.870119",
    "description": "Ongoing public infrastructure development initiative under government planning.",
    "impact": "Expected 27% improvement in public services"
  },
  {
    "name": "Eastern Peripheral Expressway Upgrade",
    "category": "water",
    "department": "Smart Cities Mission",
    "contractor": "GMR Infrastructure",
    "budget": "\u20b9780 Cr",
    "start_date": "2023-01-01",
    "completion_date": "2025-04-08",
    "status": "in progress",
    "progress": "30",
    "area": "Kolkata",
    "district": "Kolkata",
    "lat": "22.548747",
    "lng": "88.369118",
    "description": "Ongoing public infrastructure development initiative under government planning.",
    "impact": "Expected 26% improvement in public services"
  },
  {
    "name": "Multi-Speciality Government Hospital Expansion",
    "category": "road",
    "department": "Municipal Corporation",
    "contractor": "Larsen & Toubro Ltd",
    "budget": "\u20b9256 Cr",
    "start_date": "2023-10-21",
    "completion_date": "2025-01-21",
    "status": "in progress",
    "progress": "38",
    "area": "Kolkata",
    "district": "Kolkata",
    "lat": "22.61952",
    "lng": "88.40966",
    "description": "Ongoing public infrastructure development initiative under government planning.",
    "impact": "Expected 22% improvement in public services"
  },
  {
    "name": "Affordable Housing Redevelopment Scheme",
    "category": "hospital",
    "department": "Smart Cities Mission",
    "contractor": "NBCC India Ltd",
    "budget": "\u20b9267 Cr",
    "start_date": "2023-04-16",
    "completion_date": "2024-11-18",
    "status": "in progress",
    "progress": "56",
    "area": "Pune",
    "district": "Pune",
    "lat": "18.485224",
    "lng": "73.810924",
    "description": "Ongoing public infrastructure development initiative under government planning.",
    "impact": "Expected 32% improvement in public services"
  },
  {
    "name": "Water Supply Pipeline Modernization",
    "category": "water",
    "department": "Municipal Corporation",
    "contractor": "Shapoorji Pallonji Group",
    "budget": "\u20b9245 Cr",
    "start_date": "2023-06-28",
    "completion_date": "2025-07-24",
    "status": "in progress",
    "progress": "78",
    "area": "Hyderabad",
    "district": "Hyderabad",
    "lat": "17.393838",
    "lng": "78.521825",
    "description": "Ongoing public infrastructure development initiative under government planning.",
    "impact": "Expected 19% improvement in public services"
  },
  {
    "name": "Smart City Integrated Command Center",
    "category": "metro",
    "department": "Smart Cities Mission",
    "contractor": "Shapoorji Pallonji Group",
    "budget": "\u20b9192 Cr",
    "start_date": "2023-03-18",
    "completion_date": "2024-05-22",
    "status": "in progress",
    "progress": "76",
    "area": "Pune",
    "district": "Pune",
    "lat": "18.493522",
    "lng": "73.873468",
    "description": "Ongoing public infrastructure development initiative under government planning.",
    "impact": "Expected 45% improvement in public services"
  },
  {
    "name": "Metro Corridor Phase II Extension",
    "category": "hospital",
    "department": "Ministry of Road Transport and Highways",
    "contractor": "GMR Infrastructure",
    "budget": "\u20b9657 Cr",
    "start_date": "2023-07-26",
    "completion_date": "2025-11-02",
    "status": "in progress",
    "progress": "30",
    "area": "Pune",
    "district": "Pune",
    "lat": "18.49058",
    "lng": "73.839222",
    "description": "Ongoing public infrastructure development initiative under government planning.",
    "impact": "Expected 32% improvement in public services"
  },
  {
    "name": "City Bus Rapid Transit Corridor",
    "category": "building",
    "department": "Smart Cities Mission",
    "contractor": "GMR Infrastructure",
    "budget": "\u20b9636 Cr",
    "start_date": "2024-02-13",
    "completion_date": "2026-04-24",
    "status": "in progress",
    "progress": "59",
    "area": "Pune",
    "district": "Pune",
    "lat": "18.505043",
    "lng": "73.825832",
    "description": "Ongoing public infrastructure development initiative under government planning.",
    "impact": "Expected 42% improvement in public services"
  },
  {
    "name": "Urban Flood Mitigation Drainage System",
    "category": "water",
    "department": "Municipal Corporation",
    "contractor": "Shapoorji Pallonji Group",
    "budget": "\u20b9167 Cr",
    "start_date": "2023-03-20",
    "completion_date": "2025-05-31",
    "status": "in progress",
    "progress": "78",
    "area": "Mumbai",
    "district": "Mumbai Suburban",
    "lat": "19.100234",
    "lng": "72.873427",
    "description": "Ongoing public infrastructure development initiative under government planning.",
    "impact": "Expected 19% improvement in public services"
  },
  {
    "name": "Smart City Integrated Command Center",
    "category": "water",
    "department": "Ministry of Road Transport and Highways",
    "contractor": "Tata Projects Ltd",
    "budget": "\u20b9288 Cr",
    "start_date": "2023-01-28",
    "completion_date": "2025-02-27",
    "status": "in progress",
    "progress": "68",
    "area": "Pune",
    "district": "Pune",
    "lat": "18.485261",
    "lng": "73.893228",
    "description": "Ongoing public infrastructure development initiative under government planning.",
    "impact": "Expected 33% improvement in public services"
  },
  {
    "name": "Riverfront Development Project",
    "category": "metro",
    "department": "Ministry of Health",
    "contractor": "GMR Infrastructure",
    "budget": "\u20b9430 Cr",
    "start_date": "2023-12-01",
    "completion_date": "2026-02-26",
    "status": "in progress",
    "progress": "61",
    "area": "Chennai",
    "district": "Chennai",
    "lat": "13.113954",
    "lng": "80.292531",
    "description": "Ongoing public infrastructure development initiative under government planning.",
    "impact": "Expected 34% improvement in public services"
  },
  {
    "name": "Smart City Integrated Command Center",
    "category": "water",
    "department": "Urban Development Authority",
    "contractor": "NBCC India Ltd",
    "budget": "\u20b9786 Cr",
    "start_date": "2023-06-28",
    "completion_date": "2025-11-19",
    "status": "planned",
    "progress": "20",
    "area": "Pune",
    "district": "Pune",
    "lat": "18.522101",
    "lng": "73.854423",
    "description": "Ongoing public infrastructure development initiative under government planning.",
    "impact": "Expected 39% improvement in public services"
  },
  {
    "name": "Smart City Integrated Command Center",
    "category": "road",
    "department": "Ministry of Health",
    "contractor": "Tata Projects Ltd",
    "budget": "\u20b9487 Cr",
    "start_date": "2023-12-19",
    "completion_date": "2024-12-25",
    "status": "in progress",
    "progress": "77",
    "area": "Pune",
    "district": "Pune",
    "lat": "18.565237",
    "lng": "73.878994",
    "description": "Ongoing public infrastructure development initiative under government planning.",
    "impact": "Expected 25% improvement in public services"
  },
  {
    "name": "Eastern Peripheral Expressway Upgrade",
    "category": "sewage",
    "department": "Ministry of Road Transport and Highways",
    "contractor": "Larsen & Toubro Ltd",
    "budget": "\u20b9456 Cr",
    "start_date": "2023-08-16",
    "completion_date": "2024-12-09",
    "status": "planned",
    "progress": "19",
    "area": "Delhi",
    "district": "New Delhi",
    "lat": "28.631166",
    "lng": "77.175483",
    "description": "Ongoing public infrastructure development initiative under government planning.",
    "impact": "Expected 25% improvement in public services"
  },
  {
    "name": "Riverfront Development Project",
    "category": "building",
    "department": "Ministry of Road Transport and Highways",
    "contractor": "GMR Infrastructure",
    "budget": "\u20b9262 Cr",
    "start_date": "2023-03-20",
    "completion_date": "2024-06-09",
    "status": "in progress",
    "progress": "51",
    "area": "Delhi",
    "district": "New Delhi",
    "lat": "28.645739",
    "lng": "77.192459",
    "description": "Ongoing public infrastructure development initiative under government planning.",
    "impact": "Expected 38% improvement in public services"
  },
  {
    "name": "Eastern Peripheral Expressway Upgrade",
    "category": "building",
    "department": "Ministry of Health",
    "contractor": "NBCC India Ltd",
    "budget": "\u20b9467 Cr",
    "start_date": "2023-12-21",
    "completion_date": "2026-01-17",
    "status": "in progress",
    "progress": "67",
    "area": "Bangalore",
    "district": "Bangalore Urban",
    "lat": "12.990115",
    "lng": "77.644197",
    "description": "Ongoing public infrastructure development initiative under government planning.",
    "impact": "Expected 32% improvement in public services"
  },
  {
    "name": "Water Supply Pipeline Modernization",
    "category": "building",
    "department": "Municipal Corporation",
    "contractor": "Larsen & Toubro Ltd",
    "budget": "\u20b9776 Cr",
    "start_date": "2023-11-15",
    "completion_date": "2025-10-15",
    "status": "in progress",
    "progress": "87",
    "area": "Hyderabad",
    "district": "Hyderabad",
    "lat": "17.373974",
    "lng": "78.456522",
    "description": "Ongoing public infrastructure development initiative under government planning.",
    "impact": "Expected 44% improvement in public services"
  },
  {
    "name": "Multi-Speciality Government Hospital Expansion",
    "category": "building",
    "department": "Smart Cities Mission",
    "contractor": "GMR Infrastructure",
    "budget": "\u20b9397 Cr",
    "start_date": "2024-08-16",
    "completion_date": "2026-02-01",
    "status": "in progress",
    "progress": "50",
    "area": "Pune",
    "district": "Pune",
    "lat": "18.487568",
    "lng": "73.905583",
    "description": "Ongoing public infrastructure development initiative under government planning.",
    "impact": "Expected 21% improvement in public services"
  },
  {
    "name": "City Bus Rapid Transit Corridor",
    "category": "building",
    "department": "Urban Development Authority",
    "contractor": "NBCC India Ltd",
    "budget": "\u20b9628 Cr",
    "start_date": "2023-06-25",
    "completion_date": "2024-12-22",
    "status": "in progress",
    "progress": "81",
    "area": "Mumbai",
    "district": "Mumbai Suburban",
    "lat": "19.077651",
    "lng": "72.915265",
    "description": "Ongoing public infrastructure development initiative under government planning.",
    "impact": "Expected 38% improvement in public services"
  },
  {
    "name": "Urban Flood Mitigation Drainage System",
    "category": "water",
    "department": "Smart Cities Mission",
    "contractor": "Shapoorji Pallonji Group",
    "budget": "\u20b9309 Cr",
    "start_date": "2023-09-01",
    "completion_date": "2025-01-07",
    "status": "in progress",
    "progress": "40",
    "area": "Pune",
    "district": "Pune",
    "lat": "18.484067",
    "lng": "73.826396",
    "description": "Ongoing public infrastructure development initiative under government planning.",
    "impact": "Expected 28% improvement in public services"
  },
  {
    "name": "Urban Flood Mitigation Drainage System",
    "category": "road",
    "department": "Smart Cities Mission",
    "contractor": "GMR Infrastructure",
    "budget": "\u20b9133 Cr",
    "start_date": "2023-03-13",
    "completion_date": "2024-05-20",
    "status": "in progress",
    "progress": "87",
    "area": "Mumbai",
    "district": "Mumbai Suburban",
    "lat": "19.03993",
    "lng": "72.88394",
    "description": "Ongoing public infrastructure development initiative under government planning.",
    "impact": "Expected 42% improvement in public services"
  },
  {
    "name": "Smart City Integrated Command Center",
    "category": "hospital",
    "department": "Urban Development Authority",
    "contractor": "GMR Infrastructure",
    "budget": "\u20b9738 Cr",
    "start_date": "2023-05-02",
    "completion_date": "2025-05-23",
    "status": "planned",
    "progress": "11",
    "area": "Kolkata",
    "district": "Kolkata",
    "lat": "22.522819",
    "lng": "88.334732",
    "description": "Ongoing public infrastructure development initiative under government planning.",
    "impact": "Expected 38% improvement in public services"
  },
  {
    "name": "Urban Flood Mitigation Drainage System",
    "category": "building",
    "department": "Smart Cities Mission",
    "contractor": "Larsen & Toubro Ltd",
    "budget": "\u20b9434 Cr",
    "start_date": "2024-03-28",
    "completion_date": "2025-09-28",
    "status": "in progress",
    "progress": "55",
    "area": "Mumbai",
    "district": "Mumbai Suburban",
    "lat": "19.045354",
    "lng": "72.901011",
    "description": "Ongoing public infrastructure development initiative under government planning.",
    "impact": "Expected 25% improvement in public services"
  },
  {
    "name": "Affordable Housing Redevelopment Scheme",
    "category": "building",
    "department": "Ministry of Health",
    "contractor": "GMR Infrastructure",
    "budget": "\u20b9655 Cr",
    "start_date": "2024-07-27",
    "completion_date": "2026-03-26",
    "status": "in progress",
    "progress": "54",
    "area": "Hyderabad",
    "district": "Hyderabad",
    "lat": "17.352654",
    "lng": "78.487467",
    "description": "Ongoing public infrastructure development initiative under government planning.",
    "impact": "Expected 39% improvement in public services"
  },
  {
    "name": "Multi-Speciality Government Hospital Expansion",
    "category": "building",
    "department": "Municipal Corporation",
    "contractor": "Shapoorji Pallonji Group",
    "budget": "\u20b9658 Cr",
    "start_date": "2024-01-26",
    "completion_date": "2025-02-05",
    "status": "in progress",
    "progress": "34",
    "area": "Kolkata",
    "district": "Kolkata",
    "lat": "22.611433",
    "lng": "88.316207",
    "description": "Ongoing public infrastructure development initiative under government planning.",
    "impact": "Expected 27% improvement in public services"
  },
  {
    "name": "Water Supply Pipeline Modernization",
    "category": "hospital",
    "department": "Smart Cities Mission",
    "contractor": "Shapoorji Pallonji Group",
    "budget": "\u20b9639 Cr",
    "start_date": "2023-03-06",
    "completion_date": "2025-04-21",
    "status": "completed",
    "progress": "92",
    "area": "Bangalore",
    "district": "Bangalore Urban",
    "lat": "12.988082",
    "lng": "77.565726",
    "description": "Ongoing public infrastructure development initiative under government planning.",
    "impact": "Expected 24% improvement in public services"
  },
  {
    "name": "Riverfront Development Project",
    "category": "building",
    "department": "Urban Development Authority",
    "contractor": "NBCC India Ltd",
    "budget": "\u20b9460 Cr",
    "start_date": "2024-08-07",
    "completion_date": "2026-06-20",
    "status": "in progress",
    "progress": "84",
    "area": "Mumbai",
    "district": "Mumbai Suburban",
    "lat": "19.083657",
    "lng": "72.830394",
    "description": "Ongoing public infrastructure development initiative under government planning.",
    "impact": "Expected 32% improvement in public services"
  },
  {
    "name": "Smart City Integrated Command Center",
    "category": "building",
    "department": "Municipal Corporation",
    "contractor": "Larsen & Toubro Ltd",
    "budget": "\u20b9779 Cr",
    "start_date": "2024-08-01",
    "completion_date": "2026-03-16",
    "status": "in progress",
    "progress": "30",
    "area": "Chennai",
    "district": "Chennai",
    "lat": "13.09393",
    "lng": "80.268714",
    "description": "Ongoing public infrastructure development initiative under government planning.",
    "impact": "Expected 33% improvement in public services"
  },
  {
    "name": "Affordable Housing Redevelopment Scheme",
    "category": "road",
    "department": "Smart Cities Mission",
    "contractor": "GMR Infrastructure",
    "budget": "\u20b9343 Cr",
    "start_date": "2023-07-13",
    "completion_date": "2025-12-27",
    "status": "completed",
    "progress": "95",
    "area": "Bangalore",
    "district": "Bangalore Urban",
    "lat": "12.963348",
    "lng": "77.548216",
    "description": "Ongoing public infrastructure development initiative under government planning.",
    "impact": "Expected 31% improvement in public services"
  },
  {
    "name": "Smart City Integrated Command Center",
    "category": "hospital",
    "department": "Smart Cities Mission",
    "contractor": "Tata Projects Ltd",
    "budget": "\u20b920 Cr",
    "start_date": "2023-06-16",
    "completion_date": "2024-10-08",
    "status": "planned",
    "progress": "7",
    "area": "Chennai",
    "district": "Chennai",
    "lat": "13.050849",
    "lng": "80.305245",
    "description": "Ongoing public infrastructure development initiative under government planning.",
    "impact": "Expected 25% improvement in public services"
  },
  {
    "name": "Urban Flood Mitigation Drainage System",
    "category": "metro",
    "department": "Urban Development Authority",
    "contractor": "NBCC India Ltd",
    "budget": "\u20b9522 Cr",
    "start_date": "2024-01-05",
    "completion_date": "2025-09-29",
    "status": "in progress",
    "progress": "71",
    "area": "Delhi",
    "district": "New Delhi",
    "lat": "28.594235",
    "lng": "77.249516",
    "description": "Ongoing public infrastructure development initiative under government planning.",
    "impact": "Expected 16% improvement in public services"
  },
  {
    "name": "National Highway Capacity Expansion",
    "category": "road",
    "department": "Smart Cities Mission",
    "contractor": "Shapoorji Pallonji Group",
    "budget": "\u20b9238 Cr",
    "start_date": "2024-01-16",
    "completion_date": "2026-01-16",
    "status": "in progress",
    "progress": "86",
    "area": "Hyderabad",
    "district": "Hyderabad",
    "lat": "17.416698",
    "lng": "78.534656",
    "description": "Ongoing public infrastructure development initiative under government planning.",
    "impact": "Expected 38% improvement in public services"
  },
  {
    "name": "Metro Corridor Phase II Extension",
    "category": "sewage",
    "department": "Ministry of Road Transport and Highways",
    "contractor": "Shapoorji Pallonji Group",
    "budget": "\u20b9775 Cr",
    "start_date": "2023-07-10",
    "completion_date": "2024-10-05",
    "status": "planned",
    "progress": "15",
    "area": "Kolkata",
    "district": "Kolkata",
    "lat": "22.595989",
    "lng": "88.336813",
    "description": "Ongoing public infrastructure development initiative under government planning.",
    "impact": "Expected 17% improvement in public services"
  },
  {
    "name": "Metro Corridor Phase II Extension",
    "category": "hospital",
    "department": "Municipal Corporation",
    "contractor": "Shapoorji Pallonji Group",
    "budget": "\u20b9552 Cr",
    "start_date": "2023-05-11",
    "completion_date": "2024-04-27",
    "status": "in progress",
    "progress": "28",
    "area": "Chennai",
    "district": "Chennai",
    "lat": "13.103581",
    "lng": "80.27509",
    "description": "Ongoing public infrastructure development initiative under government planning.",
    "impact": "Expected 29% improvement in public services"
  },
  {
    "name": "Smart City Integrated Command Center",
    "category": "sewage",
    "department": "Municipal Corporation",
    "contractor": "GMR Infrastructure",
    "budget": "\u20b9738 Cr",
    "start_date": "2023-05-17",
    "completion_date": "2025-08-17",
    "status": "in progress",
    "progress": "23",
    "area": "Mumbai",
    "district": "Mumbai Suburban",
    "lat": "19.117347",
    "lng": "72.876975",
    "description": "Ongoing public infrastructure development initiative under government planning.",
    "impact": "Expected 20% improvement in public services"
  },
  {
    "name": "National Highway Capacity Expansion",
    "category": "water",
    "department": "Ministry of Road Transport and Highways",
    "contractor": "Shapoorji Pallonji Group",
    "budget": "\u20b9742 Cr",
    "start_date": "2024-02-28",
    "completion_date": "2025-03-04",
    "status": "in progress",
    "progress": "52",
    "area": "Mumbai",
    "district": "Mumbai Suburban",
    "lat": "19.051501",
    "lng": "72.873695",
    "description": "Ongoing public infrastructure development initiative under government planning.",
    "impact": "Expected 42% improvement in public services"
  },
  {
    "name": "National Highway Capacity Expansion",
    "category": "hospital",
    "department": "Smart Cities Mission",
    "contractor": "Larsen & Toubro Ltd",
    "budget": "\u20b995 Cr",
    "start_date": "2024-07-07",
    "completion_date": "2025-08-22",
    "status": "in progress",
    "progress": "70",
    "area": "Delhi",
    "district": "New Delhi",
    "lat": "28.614036",
    "lng": "77.212837",
    "description": "Ongoing public infrastructure development initiative under government planning.",
    "impact": "Expected 15% improvement in public services"
  },
  {
    "name": "Riverfront Development Project",
    "category": "building",
    "department": "Municipal Corporation",
    "contractor": "Larsen & Toubro Ltd",
    "budget": "\u20b9742 Cr",
    "start_date": "2024-06-02",
    "completion_date": "2026-01-23",
    "status": "in progress",
    "progress": "60",
    "area": "Mumbai",
    "district": "Mumbai Suburban",
    "lat": "19.051894",
    "lng": "72.849669",
    "description": "Ongoing public infrastructure development initiative under government planning.",
    "impact": "Expected 31% improvement in public services"
  },
  {
    "name": "Multi-Speciality Government Hospital Expansion",
    "category": "building",
    "department": "Smart Cities Mission",
    "contractor": "GMR Infrastructure",
    "budget": "\u20b9254 Cr",
    "start_date": "2023-12-16",
    "completion_date": "2025-07-17",
    "status": "in progress",
    "progress": "84",
    "area": "Delhi",
    "district": "New Delhi",
    "lat": "28.588701",
    "lng": "77.234953",
    "description": "Ongoing public infrastructure development initiative under government planning.",
    "impact": "Expected 30% improvement in public services"
  },
  {
    "name": "Smart City Integrated Command Center",
    "category": "hospital",
    "department": "Smart Cities Mission",
    "contractor": "GMR Infrastructure",
    "budget": "\u20b9568 Cr",
    "start_date": "2024-03-27",
    "completion_date": "2025-03-27",
    "status": "completed",
    "progress": "95",
    "area": "Mumbai",
    "district": "Mumbai Suburban",
    "lat": "19.045783",
    "lng": "72.867116",
    "description": "Ongoing public infrastructure development initiative under government planning.",
    "impact": "Expected 32% improvement in public services"
  },
  {
    "name": "Riverfront Development Project",
    "category": "hospital",
    "department": "Urban Development Authority",
    "contractor": "Shapoorji Pallonji Group",
    "budget": "\u20b9196 Cr",
    "start_date": "2023-01-27",
    "completion_date": "2023-12-15",
    "status": "in progress",
    "progress": "64",
    "area": "Hyderabad",
    "district": "Hyderabad",
    "lat": "17.389975",
    "lng": "78.492668",
    "description": "Ongoing public infrastructure development initiative under government planning.",
    "impact": "Expected 17% improvement in public services"
  },
  {
    "name": "National Highway Capacity Expansion",
    "category": "sewage",
    "department": "Municipal Corporation",
    "contractor": "Larsen & Toubro Ltd",
    "budget": "\u20b9723 Cr",
    "start_date": "2024-04-20",
    "completion_date": "2025-09-08",
    "status": "in progress",
    "progress": "85",
    "area": "Chennai",
    "district": "Chennai",
    "lat": "13.056232",
    "lng": "80.277628",
    "description": "Ongoing public infrastructure development initiative under government planning.",
    "impact": "Expected 16% improvement in public services"
  },
  {
    "name": "National Highway Capacity Expansion",
    "category": "metro",
    "department": "Urban Development Authority",
    "contractor": "Shapoorji Pallonji Group",
    "budget": "\u20b9161 Cr",
    "start_date": "2024-05-29",
    "completion_date": "2025-11-30",
    "status": "in progress",
    "progress": "34",
    "area": "Delhi",
    "district": "New Delhi",
    "lat": "28.56596",
    "lng": "77.228265",
    "description": "Ongoing public infrastructure development initiative under government planning.",
    "impact": "Expected 42% improvement in public services"
  },
  {
    "name": "Multi-Speciality Government Hospital Expansion",
    "category": "water",
    "department": "Municipal Corporation",
    "contractor": "GMR Infrastructure",
    "budget": "\u20b9658 Cr",
    "start_date": "2024-08-12",
    "completion_date": "2026-02-20",
    "status": "in progress",
    "progress": "69",
    "area": "Chennai",
    "district": "Chennai",
    "lat": "13.121232",
    "lng": "80.31328",
    "description": "Ongoing public infrastructure development initiative under government planning.",
    "impact": "Expected 18% improvement in public services"
  },
  {
    "name": "National Highway Capacity Expansion",
    "category": "water",
    "department": "Smart Cities Mission",
    "contractor": "NBCC India Ltd",
    "budget": "\u20b9337 Cr",
    "start_date": "2023-01-13",
    "completion_date": "2024-05-27",
    "status": "planned",
    "progress": "15",
    "area": "Mumbai",
    "district": "Mumbai Suburban",
    "lat": "19.124684",
    "lng": "72.85963",
    "description": "Ongoing public infrastructure development initiative under government planning.",
    "impact": "Expected 15% improvement in public services"
  },
  {
    "name": "Riverfront Development Project",
    "category": "water",
    "department": "Ministry of Health",
    "contractor": "GMR Infrastructure",
    "budget": "\u20b9371 Cr",
    "start_date": "2023-07-29",
    "completion_date": "2024-07-28",
    "status": "in progress",
    "progress": "29",
    "area": "Hyderabad",
    "district": "Hyderabad",
    "lat": "17.377636",
    "lng": "78.529406",
    "description": "Ongoing public infrastructure development initiative under government planning.",
    "impact": "Expected 37% improvement in public services"
  },
  {
    "name": "National Highway Capacity Expansion",
    "category": "sewage",
    "department": "Ministry of Road Transport and Highways",
    "contractor": "NBCC India Ltd",
    "budget": "\u20b9682 Cr",
    "start_date": "2024-06-26",
    "completion_date": "2025-05-24",
    "status": "in progress",
    "progress": "28",
    "area": "Pune",
    "district": "Pune",
    "lat": "18.485294",
    "lng": "73.897601",
    "description": "Ongoing public infrastructure development initiative under government planning.",
    "impact": "Expected 28% improvement in public services"
  },
  {
    "name": "Multi-Speciality Government Hospital Expansion",
    "category": "water",
    "department": "Ministry of Health",
    "contractor": "Shapoorji Pallonji Group",
    "budget": "\u20b9721 Cr",
    "start_date": "2023-02-16",
    "completion_date": "2024-06-12",
    "status": "planned",
    "progress": "13",
    "area": "Pune",
    "district": "Pune",
    "lat": "18.528309",
    "lng": "73.809899",
    "description": "Ongoing public infrastructure development initiative under government planning.",
    "impact": "Expected 16% improvement in public services"
  },
  {
    "name": "Eastern Peripheral Expressway Upgrade",
    "category": "hospital",
    "department": "Ministry of Road Transport and Highways",
    "contractor": "GMR Infrastructure",
    "budget": "\u20b9791 Cr",
    "start_date": "2023-07-17",
    "completion_date": "2025-12-29",
    "status": "completed",
    "progress": "91",
    "area": "Bangalore",
    "district": "Bangalore Urban",
    "lat": "12.988481",
    "lng": "77.621016",
    "description": "Ongoing public infrastructure development initiative under government planning.",
    "impact": "Expected 27% improvement in public services"
  },
  {
    "name": "Eastern Peripheral Expressway Upgrade",
    "category": "hospital",
    "department": "Ministry of Road Transport and Highways",
    "contractor": "GMR Infrastructure",
    "budget": "\u20b9207 Cr",
    "start_date": "2023-08-16",
    "completion_date": "2025-04-30",
    "status": "completed",
    "progress": "92",
    "area": "Hyderabad",
    "district": "Hyderabad",
    "lat": "17.372522",
    "lng": "78.495364",
    "description": "Ongoing public infrastructure development initiative under government planning.",
    "impact": "Expected 36% improvement in public services"
  },
  {
    "name": "City Bus Rapid Transit Corridor",
    "category": "water",
    "department": "Ministry of Road Transport and Highways",
    "contractor": "Larsen & Toubro Ltd",
    "budget": "\u20b9503 Cr",
    "start_date": "2023-01-07",
    "completion_date": "2024-04-20",
    "status": "in progress",
    "progress": "72",
    "area": "Bangalore",
    "district": "Bangalore Urban",
    "lat": "13.01679",
    "lng": "77.601927",
    "description": "Ongoing public infrastructure development initiative under government planning.",
    "impact": "Expected 28% improvement in public services"
  },
  {
    "name": "Eastern Peripheral Expressway Upgrade",
    "category": "water",
    "department": "Ministry of Road Transport and Highways",
    "contractor": "GMR Infrastructure",
    "budget": "\u20b9368 Cr",
    "start_date": "2024-08-22",
    "completion_date": "2026-07-06",
    "status": "in progress",
    "progress": "76",
    "area": "Mumbai",
    "district": "Mumbai Suburban",
    "lat": "19.0594",
    "lng": "72.859632",
    "description": "Ongoing public infrastructure development initiative under government planning.",
    "impact": "Expected 39% improvement in public services"
  },
  {
    "name": "Water Supply Pipeline Modernization",
    "category": "sewage",
    "department": "Urban Development Authority",
    "contractor": "Larsen & Toubro Ltd",
    "budget": "\u20b9732 Cr",
    "start_date": "2023-09-11",
    "completion_date": "2025-05-28",
    "status": "in progress",
    "progress": "70",
    "area": "Pune",
    "district": "Pune",
    "lat": "18.560488",
    "lng": "73.88303",
    "description": "Ongoing public infrastructure development initiative under government planning.",
    "impact": "Expected 25% improvement in public services"
  },
  {
    "name": "Multi-Speciality Government Hospital Expansion",
    "category": "metro",
    "department": "Ministry of Health",
    "contractor": "Larsen & Toubro Ltd",
    "budget": "\u20b923 Cr",
    "start_date": "2023-07-09",
    "completion_date": "2025-05-09",
    "status": "in progress",
    "progress": "33",
    "area": "Chennai",
    "district": "Chennai",
    "lat": "13.077531",
    "lng": "80.244544",
    "description": "Ongoing public infrastructure development initiative under government planning.",
    "impact": "Expected 27% improvement in public services"
  },
  {
    "name": "Metro Corridor Phase II Extension",
    "category": "sewage",
    "department": "Municipal Corporation",
    "contractor": "Shapoorji Pallonji Group",
    "budget": "\u20b9243 Cr",
    "start_date": "2023-07-28",
    "completion_date": "2025-05-11",
    "status": "in progress",
    "progress": "81",
    "area": "Bangalore",
    "district": "Bangalore Urban",
    "lat": "13.002778",
    "lng": "77.593016",
    "description": "Ongoing public infrastructure development initiative under government planning.",
    "impact": "Expected 17% improvement in public services"
  },
  {
    "name": "City Bus Rapid Transit Corridor",
    "category": "building",
    "department": "Ministry of Health",
    "contractor": "Shapoorji Pallonji Group",
    "budget": "\u20b9482 Cr",
    "start_date": "2023-08-15",
    "completion_date": "2025-02-08",
    "status": "in progress",
    "progress": "59",
    "area": "Bangalore",
    "district": "Bangalore Urban",
    "lat": "12.921684",
    "lng": "77.599607",
    "description": "Ongoing public infrastructure development initiative under government planning.",
    "impact": "Expected 39% improvement in public services"
  },
  {
    "name": "City Bus Rapid Transit Corridor",
    "category": "road",
    "department": "Municipal Corporation",
    "contractor": "Tata Projects Ltd",
    "budget": "\u20b9747 Cr",
    "start_date": "2023-06-29",
    "completion_date": "2025-01-28",
    "status": "planned",
    "progress": "5",
    "area": "Chennai",
    "district": "Chennai",
    "lat": "13.055983",
    "lng": "80.314114",
    "description": "Ongoing public infrastructure development initiative under government planning.",
    "impact": "Expected 29% improvement in public services"
  },
  {
    "name": "Eastern Peripheral Expressway Upgrade",
    "category": "water",
    "department": "Smart Cities Mission",
    "contractor": "Larsen & Toubro Ltd",
    "budget": "\u20b9619 Cr",
    "start_date": "2023-07-13",
    "completion_date": "2024-09-02",
    "status": "in progress",
    "progress": "29",
    "area": "Mumbai",
    "district": "Mumbai Suburban",
    "lat": "19.109502",
    "lng": "72.914397",
    "description": "Ongoing public infrastructure development initiative under government planning.",
    "impact": "Expected 16% improvement in public services"
  },
  {
    "name": "Eastern Peripheral Expressway Upgrade",
    "category": "building",
    "department": "Ministry of Road Transport and Highways",
    "contractor": "Shapoorji Pallonji Group",
    "budget": "\u20b9509 Cr",
    "start_date": "2023-02-27",
    "completion_date": "2025-01-30",
    "status": "in progress",
    "progress": "58",
    "area": "Mumbai",
    "district": "Mumbai Suburban",
    "lat": "19.07331",
    "lng": "72.897061",
    "description": "Ongoing public infrastructure development initiative under government planning.",
    "impact": "Expected 41% improvement in public services"
  },
  {
    "name": "Multi-Speciality Government Hospital Expansion",
    "category": "metro",
    "department": "Urban Development Authority",
    "contractor": "Larsen & Toubro Ltd",
    "budget": "\u20b9199 Cr",
    "start_date": "2024-02-11",
    "completion_date": "2024-12-24",
    "status": "in progress",
    "progress": "46",
    "area": "Bangalore",
    "district": "Bangalore Urban",
    "lat": "13.013507",
    "lng": "77.570046",
    "description": "Ongoing public infrastructure development initiative under government planning.",
    "impact": "Expected 15% improvement in public services"
  },
  {
    "name": "Water Supply Pipeline Modernization",
    "category": "hospital",
    "department": "Smart Cities Mission",
    "contractor": "NBCC India Ltd",
    "budget": "\u20b9260 Cr",
    "start_date": "2024-01-23",
    "completion_date": "2025-09-01",
    "status": "planned",
    "progress": "6",
    "area": "Bangalore",
    "district": "Bangalore Urban",
    "lat": "13.016913",
    "lng": "77.579394",
    "description": "Ongoing public infrastructure development initiative under government planning.",
    "impact": "Expected 15% improvement in public services"
  },
  {
    "name": "Urban Flood Mitigation Drainage System",
    "category": "road",
    "department": "Ministry of Road Transport and Highways",
    "contractor": "Tata Projects Ltd",
    "budget": "\u20b9370 Cr",
    "start_date": "2023-02-15",
    "completion_date": "2024-02-13",
    "status": "in progress",
    "progress": "45",
    "area": "Kolkata",
    "district": "Kolkata",
    "lat": "22.551169",
    "lng": "88.356224",
    "description": "Ongoing public infrastructure development initiative under government planning.",
    "impact": "Expected 26% improvement in public services"
  },
  {
    "name": "Metro Corridor Phase II Extension",
    "category": "sewage",
    "department": "Urban Development Authority",
    "contractor": "GMR Infrastructure",
    "budget": "\u20b9726 Cr",
    "start_date": "2023-11-13",
    "completion_date": "2024-11-06",
    "status": "in progress",
    "progress": "30",
    "area": "Hyderabad",
    "district": "Hyderabad",
    "lat": "17.356739",
    "lng": "78.519045",
    "description": "Ongoing public infrastructure development initiative under government planning.",
    "impact": "Expected 43% improvement in public services"
  },
  {
    "name": "Water Supply Pipeline Modernization",
    "category": "road",
    "department": "Ministry of Road Transport and Highways",
    "contractor": "Tata Projects Ltd",
    "budget": "\u20b9325 Cr",
    "start_date": "2023-11-15",
    "completion_date": "2026-02-01",
    "status": "in progress",
    "progress": "47",
    "area": "Chennai",
    "district": "Chennai",
    "lat": "13.12052",
    "lng": "80.233946",
    "description": "Ongoing public infrastructure development initiative under government planning.",
    "impact": "Expected 40% improvement in public services"
  },
  {
    "name": "Metro Corridor Phase II Extension",
    "category": "road",
    "department": "Urban Development Authority",
    "contractor": "Tata Projects Ltd",
    "budget": "\u20b961 Cr",
    "start_date": "2024-07-12",
    "completion_date": "2026-06-01",
    "status": "in progress",
    "progress": "63",
    "area": "Mumbai",
    "district": "Mumbai Suburban",
    "lat": "19.065538",
    "lng": "72.916193",
    "description": "Ongoing public infrastructure development initiative under government planning.",
    "impact": "Expected 26% improvement in public services"
  },
  {
    "name": "City Bus Rapid Transit Corridor",
    "category": "building",
    "department": "Municipal Corporation",
    "contractor": "Tata Projects Ltd",
    "budget": "\u20b9345 Cr",
    "start_date": "2023-12-18",
    "completion_date": "2025-11-04",
    "status": "in progress",
    "progress": "54",
    "area": "Bangalore",
    "district": "Bangalore Urban",
    "lat": "12.972353",
    "lng": "77.643189",
    "description": "Ongoing public infrastructure development initiative under government planning.",
    "impact": "Expected 21% improvement in public services"
  },
  {
    "name": "City Bus Rapid Transit Corridor",
    "category": "building",
    "department": "Ministry of Health",
    "contractor": "Tata Projects Ltd",
    "budget": "\u20b9766 Cr",
    "start_date": "2024-01-24",
    "completion_date": "2025-04-01",
    "status": "in progress",
    "progress": "68",
    "area": "Delhi",
    "district": "New Delhi",
    "lat": "28.634363",
    "lng": "77.181756",
    "description": "Ongoing public infrastructure development initiative under government planning.",
    "impact": "Expected 45% improvement in public services"
  },
  {
    "name": "Eastern Peripheral Expressway Upgrade",
    "category": "sewage",
    "department": "Smart Cities Mission",
    "contractor": "NBCC India Ltd",
    "budget": "\u20b9480 Cr",
    "start_date": "2024-06-06",
    "completion_date": "2026-01-05",
    "status": "in progress",
    "progress": "52",
    "area": "Pune",
    "district": "Pune",
    "lat": "18.568076",
    "lng": "73.83818",
    "description": "Ongoing public infrastructure development initiative under government planning.",
    "impact": "Expected 17% improvement in public services"
  },
  {
    "name": "Multi-Speciality Government Hospital Expansion",
    "category": "metro",
    "department": "Ministry of Road Transport and Highways",
    "contractor": "GMR Infrastructure",
    "budget": "\u20b9357 Cr",
    "start_date": "2023-04-25",
    "completion_date": "2024-12-12",
    "status": "in progress",
    "progress": "35",
    "area": "Mumbai",
    "district": "Mumbai Suburban",
    "lat": "19.06622",
    "lng": "72.8602",
    "description": "Ongoing public infrastructure development initiative under government planning.",
    "impact": "Expected 15% improvement in public services"
  },
  {
    "name": "National Highway Capacity Expansion",
    "category": "road",
    "department": "Smart Cities Mission",
    "contractor": "Larsen & Toubro Ltd",
    "budget": "\u20b9192 Cr",
    "start_date": "2024-04-06",
    "completion_date": "2025-12-03",
    "status": "in progress",
    "progress": "49",
    "area": "Kolkata",
    "district": "Kolkata",
    "lat": "22.613609",
    "lng": "88.401117",
    "description": "Ongoing public infrastructure development initiative under government planning.",
    "impact": "Expected 45% improvement in public services"
  },
  {
    "name": "Water Supply Pipeline Modernization",
    "category": "metro",
    "department": "Municipal Corporation",
    "contractor": "GMR Infrastructure",
    "budget": "\u20b9445 Cr",
    "start_date": "2023-11-01",
    "completion_date": "2024-11-10",
    "status": "in progress",
    "progress": "36",
    "area": "Delhi",
    "district": "New Delhi",
    "lat": "28.580077",
    "lng": "77.225913",
    "description": "Ongoing public infrastructure development initiative under government planning.",
    "impact": "Expected 20% improvement in public services"
  },
  {
    "name": "Urban Flood Mitigation Drainage System",
    "category": "sewage",
    "department": "Municipal Corporation",
    "contractor": "GMR Infrastructure",
    "budget": "\u20b9695 Cr",
    "start_date": "2023-10-31",
    "completion_date": "2025-06-23",
    "status": "in progress",
    "progress": "85",
    "area": "Kolkata",
    "district": "Kolkata",
    "lat": "22.606985",
    "lng": "88.392726",
    "description": "Ongoing public infrastructure development initiative under government planning.",
    "impact": "Expected 32% improvement in public services"
  },
  {
    "name": "Smart City Integrated Command Center",
    "category": "road",
    "department": "Urban Development Authority",
    "contractor": "Shapoorji Pallonji Group",
    "budget": "\u20b9715 Cr",
    "start_date": "2024-02-26",
    "completion_date": "2025-05-12",
    "status": "in progress",
    "progress": "45",
    "area": "Delhi",
    "district": "New Delhi",
    "lat": "28.655352",
    "lng": "77.17052",
    "description": "Ongoing public infrastructure development initiative under government planning.",
    "impact": "Expected 17% improvement in public services"
  },
  {
    "name": "National Highway Capacity Expansion",
    "category": "metro",
    "department": "Urban Development Authority",
    "contractor": "NBCC India Ltd",
    "budget": "\u20b9370 Cr",
    "start_date": "2023-12-25",
    "completion_date": "2026-05-30",
    "status": "in progress",
    "progress": "43",
    "area": "Delhi",
    "district": "New Delhi",
    "lat": "28.645926",
    "lng": "77.190674",
    "description": "Ongoing public infrastructure development initiative under government planning.",
    "impact": "Expected 29% improvement in public services"
  },
  {
    "name": "Water Supply Pipeline Modernization",
    "category": "hospital",
    "department": "Ministry of Road Transport and Highways",
    "contractor": "GMR Infrastructure",
    "budget": "\u20b9714 Cr",
    "start_date": "2023-05-18",
    "completion_date": "2025-10-20",
    "status": "in progress",
    "progress": "62",
    "area": "Chennai",
    "district": "Chennai",
    "lat": "13.084885",
    "lng": "80.238821",
    "description": "Ongoing public infrastructure development initiative under government planning.",
    "impact": "Expected 24% improvement in public services"
  },
  {
    "name": "Multi-Speciality Government Hospital Expansion",
    "category": "sewage",
    "department": "Ministry of Health",
    "contractor": "Tata Projects Ltd",
    "budget": "\u20b9366 Cr",
    "start_date": "2023-01-03",
    "completion_date": "2025-05-07",
    "status": "in progress",
    "progress": "80",
    "area": "Bangalore",
    "district": "Bangalore Urban",
    "lat": "13.019221",
    "lng": "77.6239",
    "description": "Ongoing public infrastructure development initiative under government planning.",
    "impact": "Expected 45% improvement in public services"
  },
  {
    "name": "City Bus Rapid Transit Corridor",
    "category": "water",
    "department": "Smart Cities Mission",
    "contractor": "Tata Projects Ltd",
    "budget": "\u20b9634 Cr",
    "start_date": "2024-05-24",
    "completion_date": "2025-07-02",
    "status": "in progress",
    "progress": "72",
    "area": "Kolkata",
    "district": "Kolkata",
    "lat": "22.525339",
    "lng": "88.405533",
    "description": "Ongoing public infrastructure development initiative under government planning.",
    "impact": "Expected 26% improvement in public services"
  },
  {
    "name": "National Highway Capacity Expansion",
    "category": "building",
    "department": "Ministry of Health",
    "contractor": "Tata Projects Ltd",
    "budget": "\u20b942 Cr",
    "start_date": "2023-02-11",
    "completion_date": "2024-03-30",
    "status": "in progress",
    "progress": "74",
    "area": "Delhi",
    "district": "New Delhi",
    "lat": "28.581799",
    "lng": "77.183249",
    "description": "Ongoing public infrastructure development initiative under government planning.",
    "impact": "Expected 25% improvement in public services"
  },
  {
    "name": "Urban Flood Mitigation Drainage System",
    "category": "hospital",
    "department": "Ministry of Road Transport and Highways",
    "contractor": "Shapoorji Pallonji Group",
    "budget": "\u20b9320 Cr",
    "start_date": "2024-03-24",
    "completion_date": "2025-07-25",
    "status": "in progress",
    "progress": "74",
    "area": "Kolkata",
    "district": "Kolkata",
    "lat": "22.557945",
    "lng": "88.400207",
    "description": "Ongoing public infrastructure development initiative under government planning.",
    "impact": "Expected 20% improvement in public services"
  },
  {
    "name": "Urban Flood Mitigation Drainage System",
    "category": "sewage",
    "department": "Smart Cities Mission",
    "contractor": "Larsen & Toubro Ltd",
    "budget": "\u20b9774 Cr",
    "start_date": "2023-03-19",
    "completion_date": "2024-12-19",
    "status": "in progress",
    "progress": "57",
    "area": "Bangalore",
    "district": "Bangalore Urban",
    "lat": "13.012895",
    "lng": "77.591274",
    "description": "Ongoing public infrastructure development initiative under government planning.",
    "impact": "Expected 44% improvement in public services"
  },
  {
    "name": "Eastern Peripheral Expressway Upgrade",
    "category": "metro",
    "department": "Ministry of Road Transport and Highways",
    "contractor": "Tata Projects Ltd",
    "budget": "\u20b9672 Cr",
    "start_date": "2023-06-15",
    "completion_date": "2025-06-22",
    "status": "in progress",
    "progress": "38",
    "area": "Chennai",
    "district": "Chennai",
    "lat": "13.114985",
    "lng": "80.271112",
    "description": "Ongoing public infrastructure development initiative under government planning.",
    "impact": "Expected 21% improvement in public services"
  },
  {
    "name": "Urban Flood Mitigation Drainage System",
    "category": "hospital",
    "department": "Ministry of Health",
    "contractor": "Larsen & Toubro Ltd",
    "budget": "\u20b9154 Cr",
    "start_date": "2023-04-02",
    "completion_date": "2024-04-08",
    "status": "completed",
    "progress": "95",
    "area": "Mumbai",
    "district": "Mumbai Suburban",
    "lat": "19.116255",
    "lng": "72.864612",
    "description": "Ongoing public infrastructure development initiative under government planning.",
    "impact": "Expected 34% improvement in public services"
  },
  {
    "name": "Metro Corridor Phase II Extension",
    "category": "metro",
    "department": "Ministry of Health",
    "contractor": "Shapoorji Pallonji Group",
    "budget": "\u20b9433 Cr",
    "start_date": "2023-12-23",
    "completion_date": "2025-01-31",
    "status": "in progress",
    "progress": "56",
    "area": "Delhi",
    "district": "New Delhi",
    "lat": "28.626747",
    "lng": "77.232193",
    "description": "Ongoing public infrastructure development initiative under government planning.",
    "impact": "Expected 16% improvement in public services"
  }
]